<?xml version="1.0" encoding="UTF-8"?>
<configuration>
    <!-- Development: human-readable console output -->
    <springProfile name="default,local">
        <appender name="CONSOLE" class="ch.qos.logback.core.ConsoleAppender">
            <encoder>
                <pattern>%d{HH:mm:ss.SSS} [%thread] %-5level %logger{36} - %msg%n</pattern>
            </encoder>
        </appender>
        <root level="INFO">
            <appender-ref ref="CONSOLE"/>
        </root>
    </springProfile>

    <!-- Production: structured JSON logging -->
    <springProfile name="prod">
        <appender name="CONSOLE" class="ch.qos.logback.core.ConsoleAppender">
            <encoder>
                <pattern>%d{yyyy-MM-dd'T'HH:mm:ss.SSSZ} %level [%thread] %logger{40} - %msg%n</pattern>
            </encoder>
        </appender>

        <appender name="FILE" class="ch.qos.logback.core.rolling.RollingFileAppender">
            <file>/opt/quickshare/logs/quickshare.log</file>
            <rollingPolicy class="ch.qos.logback.core.rolling.SizeAndTimeBasedRollingPolicy">
                <fileNamePattern>/opt/quickshare/logs/quickshare.%d{yyyy-MM-dd}.%i.log.gz</fileNamePattern>
                <maxFileSize>50MB</maxFileSize>
                <maxHistory>30</maxHistory>
                <totalSizeCap>1GB</totalSizeCap>
            </rollingPolicy>
            <encoder>
                <pattern>%d{yyyy-MM-dd'T'HH:mm:ss.SSSZ} %level [%thread] %logger{40} - %msg%n</pattern>
            </encoder>
        </appender>

        <root level="INFO">
            <appender-ref ref="CONSOLE"/>
            <appender-ref ref="FILE"/>
        </root>

        <!-- Reduce noise from libraries -->
        <logger name="org.apache.ibatis" level="WARN"/>
        <logger name="com.zaxxer.hikari" level="WARN"/>
        <logger name="org.flywaydb" level="INFO"/>
    </springProfile>
</configuration>
